markerpath/__init__.py
markerpath/markerpath.py
markerpath/markerpath_global.py
markerpath-0.1.17.dist-info/LICENSE
markerpath-0.1.17.dist-info/METADATA
markerpath-0.1.17.dist-info/WHEEL
markerpath-0.1.17.dist-info/top_level.txt
markerpath-0.1.17.dist-info/RECORD
