Metadata-Version: 2.1
Name: markerpath
Version: 0.1.17
Summary: All imports are relative to the presence of the marker file
Home-page: https://github.com/
Author: gg61021277
Author-email: gg61021277@gmail.com
Classifier: Programming Language :: Python :: 3
Classifier: License :: OSI Approved :: MIT License
Classifier: Operating System :: OS Independent
Requires-Python: >=3.6
License-File: LICENSE
